{
  "overall_mood": {
    "word": "焦虑",
    "reason": "平台合规严查致店铺冻结频发，税务稽查案例曝光引发恐慌，AI 工具安全隐患加剧卖家对资产安全的焦虑。",
    "source_urls": [
      "https://www.cifnews.com/article/184783",
      "https://www.cifnews.com/article/185063",
      "https://www.cifnews.com/article/184088"
    ]
  },
  "top_3_pain_points": [
    {
      "name": "知识产权侵权风暴",
      "scene": "上架前没查专利，突然收到侵权通知，链接下架资金冻结，半年白干。",
      "product_idea": "AI 专利风险预扫描插件，上架前自动比对全球专利库。",
      "source_urls": [
        "https://www.cifnews.com/article/185067",
        "https://www.cifnews.com/article/185019",
        "https://www.52by.com/article/215481"
      ]
    },
    {
      "name": "平台政策与成本双压",
      "scene": "FBA 又涨价，定价新规不让虚标划线价，利润薄如纸，广告还烧不动。",
      "product_idea": "合规定价与利润测算工具，自动适配平台新规避免违规。",
      "source_urls": [
        "https://www.cifnews.com/article/184859",
        "https://www.cifnews.com/article/184913",
        "https://www.cifnews.com/article/184939"
      ]
    },
    {
      "name": "税务合规与资产暴露",
      "scene": "私账收款被稽查，补税罚款好几千万，海外房产信息也要交换回国，睡不着觉。",
      "product_idea": "跨境税务合规自查 SaaS，监控资金流与海外资产税务风险。",
      "source_urls": [
        "https://www.cifnews.com/article/184783",
        "https://www.52by.com/article/215650"
      ]
    }
  ],
  "core_news_impact": [
    {
      "title": "亚马逊宣布欧美站 FBA 配送费涨价",
      "impact_type": "cost",
      "interpretation": "北美站点 FBA 配送费增加 3.5%，欧洲站点增加 1.5%，直接压缩卖家利润空间，需重新核算定价模型。",
      "source_urls": [
        "https://www.cifnews.com/article/184859"
      ]
    },
    {
      "title": "深圳 3C 大卖私账收款偷税被抓",
      "impact_type": "cost",
      "interpretation": "税务局查处隐匿 1.2 亿收入案件，追缴税款并罚款 2800 多万，警示私账收款风险，合规成本上升。",
      "source_urls": [
        "https://www.cifnews.com/article/184783"
      ]
    }
  ],
  "workflow_insights": [
    {
      "title": "乐器创业者低成本快速建独立站指南",
      "detail": "7 天快速上线流程，聚焦内容营销与垂直社群引流，避免高额广告投入，适合预算有限的初创品牌。",
      "tools": "Ueeshop, Shopify, TikTok, Facebook Groups",
      "source_urls": [
        "https://www.52by.com/article/215529"
      ]
    },
    {
      "title": "亚马逊 VC 底层招商逻辑揭秘",
      "detail": "VM 经理关注单类目 GMV、独立站运营能力及多渠道供给资质，而非单纯总销售额，需专注深耕核心品类。",
      "tools": "Independent site, Multi-channel management",
      "source_urls": [
        "https://www.cifnews.com/article/185012"
      ]
    }
  ],
  "raw_quotes": [
    {
      "text": "我们特意找的是平台自己推荐的服务商，检测流程、报告规范都按要求来做，现在突然说不合格，商品卖不了，检测费也全打了水漂。",
      "source_label": "雨果网",
      "source_urls": [
        "https://www.cifnews.com/article/184939"
      ]
    },
    {
      "text": "世界蠢得不可思议，我也是。",
      "source_label": "雨果网",
      "source_urls": [
        "https://www.cifnews.com/article/185034"
      ]
    },
    {
      "text": "花 50 元找人远程安装 OpenClaw，结果安装当天，店铺后台就出现异常登录记录，绑定的信用卡被莫名刷走近万元。",
      "source_label": "雨果网",
      "source_urls": [
        "https://www.cifnews.com/article/184088"
      ]
    }
  ]
}